jam_rocksdict-0.3.27.dist-info/METADATA
jam_rocksdict-0.3.27.dist-info/WHEEL
jam_rocksdict-0.3.27.dist-info/licenses/LICENSE
rocksdict/__init__.py
rocksdict/py.typed
rocksdict/rocksdict.cpython-313-x86_64-linux-gnu.so
rocksdict/rocksdict.pyi
jam_rocksdict-0.3.27.dist-info/RECORD
